devtracker/__init__.py
devtracker/__main__.py
devtracker/dir_and_path_helpers.py
devtracker/report.py
devtracker/test_devtracker.py
devtracker/time.py
devtracker/time_and_date_helpers.py
devtracker-0.1.0.dist-info/LICENSE.md
devtracker-0.1.0.dist-info/METADATA
devtracker-0.1.0.dist-info/WHEEL
devtracker-0.1.0.dist-info/entry_points.txt
devtracker-0.1.0.dist-info/top_level.txt
devtracker-0.1.0.dist-info/RECORD
