Metadata-Version: 2.1
Name: devtracker
Version: 0.1.0
Summary: A simple way to track time spent working on projects.
Home-page: https://github.com/ConSou/devtracker
Author: ConSou
Author-email: conorsouhrada@gmail.com
License: UNKNOWN
Platform: UNKNOWN
Classifier: Programming Language :: Python :: 3
Classifier: License :: OSI Approved :: MIT License
Classifier: Operating System :: OS Independent
